<DOC>
	<DOCNO>NCT02030873</DOCNO>
	<brief_summary>The purpose study investigate effect virtual simulation train mastoidectomy dissection performance otorhinolaryngology trainee , explore performance assessment use final-product analysis approach explore role cognitive load .</brief_summary>
	<brief_title>The Effect Virtual Simulation Training Mastoidectomy</brief_title>
	<detailed_description>Traditional dissection train temporal bone surgery evidence-based yet gold standard . In recent year Visible Ear Simulator use introduction mastoidectomy Danish temporal bone course curriculum let participant move dissection training order maximize yield dissection training . Instructors impression participant perform good dissection simulator training session introduce . Our pilot study suggest participant perform good simulator compare traditional dissection training . This could due reduction cognitive load virtual simulator . These observation lead hypothesis virtual simulation train mastoidectomy provide effect improve performance traditional dissection training .</detailed_description>
	<criteria>Resident otorhinolaryngology postgraduate year 25 Informed write consent Previous participation formal mastoidectomy train virtual simulator</criteria>
	<gender>All</gender>
	<minimum_age>18 Years</minimum_age>
	<maximum_age>N/A</maximum_age>
	<verification_date>May 2015</verification_date>
	<keyword>virtual simulation</keyword>
	<keyword>temporal bone</keyword>
	<keyword>surgical training</keyword>
	<keyword>medical education</keyword>
	<keyword>self-directed learning</keyword>
	<keyword>final product assessment</keyword>
	<keyword>cognitive load</keyword>
	<keyword>reaction time</keyword>
	<keyword>skill train</keyword>
	<keyword>simulator metric</keyword>
</DOC>