<DOC>
	<DOCNO>NCT01337115</DOCNO>
	<brief_summary>The purpose study determine addition sciatic nerve block ( SNB ) continuous femoral nerve block ( CFNB ) improve post-operative analgesia knee arthroplasty .</brief_summary>
	<brief_title>Effect Sciatic Block ( SNB ) Combined With Continuous Femoral Block ( CFNB ) Pain Scores After Knee Arthroplasty</brief_title>
	<detailed_description>Background : Postoperative pain total knee replacement /arthroplasty ( TKA ) major concern . It severe pain 60 % patient moderate 30 % . Continuous femoral nerve block ( CFNB ) consider excellent choice regional anesthesia major knee repair controversy need supplemental obturator sciatic nerve block achieve well postoperative analgesia . A recent meta-analysis state sufficient evidence recommend discharge association . Objectives : We aim assess efficacy association sciatic nerve block ( SNB ) continuous femoral nerve block ( CFNB ) reduce postoperative pain patient submit TKA . Methods : A randomized control study 50 patient submit TKA . Control group receive femoral nerve block catheter general anesthesia induce intervention group get similar block plus single shot SNB general anesthesia . Both group start continuous local anesthetic infusion femoral catheter end surgery supplemental oral diclofenac paracetamol . Pain score measure 24h postoperatively , side effect patient satisfaction monitor .</detailed_description>
	<mesh_term>Pain , Postoperative</mesh_term>
	<mesh_term>Anesthetics</mesh_term>
	<mesh_term>Ropivacaine</mesh_term>
	<mesh_term>Anesthetics , Local</mesh_term>
	<criteria>Unilateral total knee replacement Contraindication general anesthesia Infection puncture site Coagulation disorder Preexistent neuropathy Allergies local anesthetic , paracetamol , diclofenac tramadol Severe dyspepsia Less 50kg weigh Body Mass Index ( BMI ) great 40 American Society Anesthesiologists ( ASA ) Physical Status 4 5 Absence capacity use Visual Analog Score ( VAS ) scale Refusal give inform consent</criteria>
	<gender>All</gender>
	<minimum_age>N/A</minimum_age>
	<maximum_age>N/A</maximum_age>
	<verification_date>May 2012</verification_date>
	<keyword>Postoperative pain</keyword>
	<keyword>Knee arthroplasty</keyword>
	<keyword>Peripheral nerve block</keyword>
	<keyword>Sciatic nerve block</keyword>
	<keyword>Femoral nerve block</keyword>
</DOC>