<DOC>
	<DOC>NCT00629733</DOC>
	<brief_summary>Clinical trial to evaluate the tolerability and pharmacokinetics of a new ultra low molecular weight heparin (RO-14) administered subcutaneously increasing single-doses to healthy male volunteers</brief_summary>
	<brief_title>Clinical Trial to Evaluate the Tolerability and Pharmacokinetics of a New Ultra Low Molecular Weight Heparin (RO-14) Administered Subcutaneously Increasing Single-doses to Healthy Male Volunteers</brief_title>
	<detailed_description />
	<mesh_term>Heparin, Low-Molecular-Weight</mesh_term>
	<mesh_term>Dalteparin</mesh_term>
	<mesh_term>Heparin</mesh_term>
	<criteria>1. Healthy volunteers: male subjects aged between 18 and 45 years 2. Body weight: 6575 Kg 3. Not meaningful abnormalities in physical examination and in clinical history 4. Without evidence of significant organic or psychiatric illness 5. Hemogram, biochemistry and coagulation in normal values established in the reference range of the local hospital laboratory 6. Vital signs (blood pressure, heart beat rate and body temperature) and EKG within normal range 7. Healthy volunteers who are not participating in another clinical trial or have not done so in the past 2 months 8. Not give blood in the last 4 weeks. 9. Healthy male volunteers who have not received heparin in the past 10. Healthy male volunteers who have accepted to participate in the study and have signed the written informed consent 1. Previous history of alcoholism, drug dependency, drug abuse or habitual psychoactive drugs consumption 2. Important consumption of exciting drinks: alcohol consumption &gt; 30 g/day; coffee, tea, cola &gt; 5 /day 3. Allergy, idiosyncrasy or hypersensitivity to medicines 4. Healthy volunteers who are receiving another medication in the past 15 days 5. Positive serology of hepatitis B, C or HIV 6. Cardiovascular, respiratory, renal, hepatic, endocrine, gastrointestinal, hematologic, psychiatric, neurological and others events 7. Mayor Surgery in the last 6 months 8. Smoking &gt; 10 cigarettes / day 9. Ethanol, cannabis, cocaine, amphetamine, benzodiazepine or opiate in urine 10. Healthy volunteers with a familiar history evident hemorrhagic episodes</criteria>
	<gender>Male</gender>
	<minimum_age>18 Years</minimum_age>
	<maximum_age>45 Years</maximum_age>
	<verification_date>June 2011</verification_date>
	<keyword>pharmacokinetics</keyword>
	<keyword>ultra low molecular weight heparin</keyword>
</DOC>