<DOC>
	<DOCNO>NCT02737527</DOCNO>
	<brief_summary>This study compare efficacy ultrasound fluoroscope guidance lumbar sympathetic block ( LSB ) . The goal study ; 1 ) To show US-guided LSB result short performance time compare fluoroscope-guided LSB , 2 ) To evaluate efficacy safety US-guided LSB , 3 ) To verify US-guided LSB similar success rate fluoroscope-guided LSB . 50 patient suppose undergo LSB due sympathetically maintain pain , satisfy criterion inclusion exclusion , voluntarily sign informed consent enrol .</brief_summary>
	<brief_title>Comparison Efficacy Ultrasound With Fluoroscopy Guidance Lumbar Sympathetic Block</brief_title>
	<detailed_description />
	<mesh_term>Peripheral Nervous System Diseases</mesh_term>
	<mesh_term>Polyneuropathies</mesh_term>
	<mesh_term>Neuralgia</mesh_term>
	<mesh_term>Neuralgia , Postherpetic</mesh_term>
	<mesh_term>Complex Regional Pain Syndromes</mesh_term>
	<mesh_term>Reflex Sympathetic Dystrophy</mesh_term>
	<mesh_term>Diabetic Neuropathies</mesh_term>
	<mesh_term>Levobupivacaine</mesh_term>
	<mesh_term>Bupivacaine</mesh_term>
	<criteria>Patients sympatheticallymediated pain suppose undergo LSB procedure ( e.g . pain asymmetric skin temperature low limb previous thermography , small fiber disorder previous quantitative sudomotor axon reflex test ( QSART ) , vascular insufficiency low extremity , diabetic polyneuropathy , postherpetic neuralgia , complex regional pain syndrome , cancerrelated neuropathic pain chemotherapyinduced peripheral neuropathy , low extremity neuropathy , low extremity crush injury etc . ) Numeric rating scale ( NRS ) ≥ 4/10 Failure previous conservative treatment , physiotherapy , oral medication , noninvasive treatment Previous lumbar sympathetic neurolysis Bleeding tendency Local infection Allergy local anesthetic contrast medium Pregnancy Severe variation near procedure site—scoliosis , tumor , abdominal aneurysm , etc . BMI ≥ 30 kg/m2 Cognitive dysfunction</criteria>
	<gender>All</gender>
	<minimum_age>18 Years</minimum_age>
	<maximum_age>85 Years</maximum_age>
	<verification_date>June 2016</verification_date>
	<keyword>ultrasound</keyword>
	<keyword>lumbar sympathetic block</keyword>
</DOC>