<DOC>
	<DOCNO>NCT01464502</DOCNO>
	<brief_summary>Heart failure patient may benefit special pacemaker implant make heart pump coordinate efficient way Cardiac Resynchronisation Therapy ( CRT ) . For heart pump well necessary pacing wire place optimal position . Only two third people respond CRT may non-ideal pace wire position . A potential marker response change heart pump pressure change time . The aim study use specialise wire main pump chamber heart record pressure change pace lead various position determine optimal position . It postulate improved pressure change increase proportion responder . Pilot study work show work technically feasible safe . The initial data publish highly regarded scientific journal . This main study multicentre randomise control trial whereby patient randomise either standard treatment pressure wireguided treatment . The patient pressurewire guided arm specialise wire implant main pump chamber heart via blood vessel top leg ( less commonly blood vessel wrist ) . This measure acute pressure change time pace lead position site give great change pressure . If patient pressurewire guided arm fare well receive standard treatment may alter large proportion heart failure patient treat around world . The study require 282 patient likely take two year complete .</brief_summary>
	<brief_title>Pressure Wire Guided Cardiac Resynchronisation Therapy</brief_title>
	<detailed_description />
	<mesh_term>Heart Failure</mesh_term>
	<criteria>Patients fulfil standard criterion CRT Ischaemic nonischaemic heart failure Contraindication pressure wire assessment include : Severe aortic valve disease Mechanical aortic valve replacement Severe peripheral vascular disease LV thrombus</criteria>
	<gender>All</gender>
	<minimum_age>18 Years</minimum_age>
	<maximum_age>N/A</maximum_age>
	<verification_date>April 2017</verification_date>
	<keyword>Heart failure</keyword>
	<keyword>Cardiac resynchronisation therapy</keyword>
	<keyword>Acute haemodynamic response</keyword>
	<keyword>Responder</keyword>
</DOC>