<DOC>
	<DOCNO>NCT00180934</DOCNO>
	<brief_summary>Interest reirradiation concomitant chemotherapy salvage surgery recurrence head cancer irradiated area : multicentric Phase III randomize trial</brief_summary>
	<brief_title>Reirradiation With Concomitant Chemotherapy After Salvage Surgery Recurrence Head Neck Cancer Irradiated Area</brief_title>
	<detailed_description />
	<mesh_term>Recurrence</mesh_term>
	<mesh_term>Head Neck Neoplasms</mesh_term>
	<criteria>head neck squamous cancer sex &gt; =18 year recurrence treat surgery initially treat radiotherapy write informed consent entry time</criteria>
	<gender>All</gender>
	<minimum_age>18 Years</minimum_age>
	<maximum_age>N/A</maximum_age>
	<verification_date>September 2005</verification_date>
</DOC>