<DOC>
	<DOCNO>NCT00323453</DOCNO>
	<brief_summary>The purpose study determine whether incidence surgical site wound infection reduce open appendectomy patient use Alexis速 wound retractor .</brief_summary>
	<brief_title>Wound Infection Alexis Wound Retractor</brief_title>
	<detailed_description>Aim : This randomized comparison open appendectomy use metal retractor open appendectomy use Alexis速 wound retractor patient simple complicated appendicitis . The study design order minimize bias standardize two procedure blind patient nurse preoperative postoperative period . After obtain informed consent , inform assent minor , subject randomize either two group : one group undergo standard open appendectomy use traditional metal retractor . The second group undergo open appendectomy use Alexis速 wound retractor . Pre-operative antibiotic Zosyn give prior skin incision . Skin prep betadine , duraprep gel prep . After enter peritoneal cavity , Alexis速 retractor introduce use maintain retraction duration surgery . In simple appendicitis , patient receive one dose antibiotic six hour surgery . The patient receive oral antibiotic discharge . In complicated appendicitis , patient give Zosyn afebrile 24 hour normal white blood cell count . The patient discharge oral antibiotic . Follow occur 14th 21st post operative day . At test cure visit , wound check erythema , drainage , open . It assess whether subject receive medical attention receive medication since discharge .</detailed_description>
	<mesh_term>Infection</mesh_term>
	<mesh_term>Appendicitis</mesh_term>
	<mesh_term>Wound Infection</mesh_term>
	<mesh_term>Surgical Wound Infection</mesh_term>
	<criteria>Clinical diagnosis appendicitis Open appendectomy Ability attend followup visit</criteria>
	<gender>All</gender>
	<minimum_age>18 Years</minimum_age>
	<maximum_age>N/A</maximum_age>
	<verification_date>May 2009</verification_date>
	<keyword>Appendectomy</keyword>
	<keyword>Surgery</keyword>
	<keyword>Infection</keyword>
</DOC>