<DOC>
	<DOCNO>NCT00000926</DOCNO>
	<brief_summary>The purpose study see nonoxynol-9 ( N-9 ) gel use vagina prevent spread HIV . Most people HIV world today live southern Africa . Because population likely use condom , HIV-prevention method woman control need . N-9 use vagina may help prevent spread HIV sexually transmit disease .</brief_summary>
	<brief_title>A Study Nonoxynol-9 ( N-9 ) HIV Infection</brief_title>
	<detailed_description>Intravaginal application N-9 may help protect woman HIV STD infection . Low rate condom use sub-Saharan African population , constitute majority HIV infection , dictate need prophylactic method woman control . This trial conduct Zimbabwe Malawi . The Phase III trial precede 2-week safety acceptability pilot study determine extent genital irritation cause N-9 placebo . Following pilot study prior screen enrollment Phase III trial , potential volunteer participate 2-month behavioral counseling program encourage use condom . Only participant decide consistent condom user enrol main study . Study participant give N-9 gel placebo use time vaginal sexual intercourse 18 36 month . Participants follow-up evaluation month ; pelvic exam blood test perform every third month .</detailed_description>
	<mesh_term>Infection</mesh_term>
	<mesh_term>Communicable Diseases</mesh_term>
	<mesh_term>HIV Infections</mesh_term>
	<mesh_term>Acquired Immunodeficiency Syndrome</mesh_term>
	<mesh_term>Nonoxynol</mesh_term>
	<criteria>Inclusion Criteria Volunteers may eligible : Are HIVnegative . Are sexually active expect vaginal intercourse least twice week study . Are willing keep diary sexual behavior N9 use . Are willing regular clinic visit include pelvic exam . Are least 18 year old . Are female . Exclusion Criteria Volunteers eligible : Have child abortion past 42 day . Are allergic latex N9 . Have genital sore . Have syphilis , chlamydia , gonorrhea , trichomoniasis . Are enrol another study product like N9 . Expect use another vaginal product N9 study . Are pregnant .</criteria>
	<gender>Female</gender>
	<minimum_age>18 Years</minimum_age>
	<maximum_age>N/A</maximum_age>
	<verification_date>May 2012</verification_date>
	<keyword>Nonoxynol</keyword>
</DOC>