<DOC>
	<DOCNO>NCT00062985</DOCNO>
	<brief_summary>The aim present study evaluate effectiveness two different delivery format weight management manage care set . Mail-based weight counsel phone-based weight counsel compare control condition . Primary outcomes participation rate program , weight change , cost .</brief_summary>
	<brief_title>Obesity Treatment Managed Care Setting</brief_title>
	<detailed_description />
	<mesh_term>Obesity</mesh_term>
	<mesh_term>Weight Loss</mesh_term>
	<criteria>least 18 year age BMI ≥ 27.8 kg/m2 men BMI ≥ 27.3 kg/m2 nonpregnant lactating woman</criteria>
	<gender>All</gender>
	<minimum_age>18 Years</minimum_age>
	<maximum_age>N/A</maximum_age>
	<verification_date>November 2010</verification_date>
	<keyword>obesity treatment</keyword>
	<keyword>weight management</keyword>
	<keyword>manage care</keyword>
</DOC>