<DOC>
	<DOCNO>NCT01961895</DOCNO>
	<brief_summary>The purpose study evaluate efficacy perioperative continuous lumbar plexus block reduce risk cardiac ischemic event elderly patient undergo surgery hip fracture , express reduction ischemic event per subject .</brief_summary>
	<brief_title>Lumbar Plexus Block Upon Incidence Ischemic Cardiovascular Events Elderly Patients With Hip Fracture</brief_title>
	<detailed_description />
	<mesh_term>Fractures , Bone</mesh_term>
	<mesh_term>Ischemia</mesh_term>
	<mesh_term>Hip Fractures</mesh_term>
	<mesh_term>Myocardial Ischemia</mesh_term>
	<mesh_term>Coronary Artery Disease</mesh_term>
	<criteria>Patients hip fracture within 48 hour evolution Known coronary artery disease : Previous myocardial infarction Chronic stable angina Atypical angina positive exercise test coronary flow failure . Evidence coronary artery disease ultrasound , scintigraphic angiographic compatible Patients least two risk factor coronary heart disease define Wallace ( 1998 ) Patients receive orthopedic treatment . Patients coagulopathy , clinic laboratory . Patients sepsis infection catheter insertion site lumbar plexus . Patients neurological disease evolve . Patients disorient , dementia . CKD stage IV National Kidney Foundation ( 2 ) Glomerular filtration rate 15 29 mL/min/1 , 73 m2 Patients unable use Numeric Rating Scale ( NRS ) ass pain . Patients nonsinus rhythm conduction abnormality ( right bundle branch block leave , atrioventricular block ) admission ECG Patients pacemaker . Enrolled patient acute coronary syndrome decompensated cardiovascular disease entry . Allergy drug protocol . Inability understand unaided sign inform consent .</criteria>
	<gender>All</gender>
	<minimum_age>N/A</minimum_age>
	<maximum_age>N/A</maximum_age>
	<verification_date>October 2013</verification_date>
	<keyword>Continuous lumbar plexus ( LP ) block analgesia</keyword>
</DOC>